MAC_HW_plus/param.v
`define DATA_WIDTH 64

MAC_HW_plus/MAC_new.v
module MAC_new (
    input clk ,
    input mulsel,
    input addsel,
    input [`DATA_WIDTH-1:0] data_0 ,
    input [`DATA_WIDTH-1:0] data_1 ,
    output reg [`DATA_WIDTH-1:0] mac_out
);
reg [`DATA_WIDTH-1:0] mult_out ;
initial begin
    mult_out=1;
end
always @(posedge clk) begin
    mult_out <= (mulsel)?(data_0 * mult_out):(data_0 * data_1);
    mac_out <=  (addsel)? (mult_out+mac_out):(mult_out);
end

endmodule

MAC_HW_plus/FIFO_64x4.v
`include "param.v"

module FIFO_64x4
// #(parameter DATA_WIDTH = `DATA_WIDTH)
(output n_full , input [`DATA_WIDTH-1:0] Din , output reg [`DATA_WIDTH-1:0] Dout , input clk_in , input clk_out , input WE , input RE , output n_empty);
reg [`DATA_WIDTH-1:0] RAM [0:3] ; 
reg [2:0] in_count , out_count ;
initial begin
    in_count = 2'd0 ;
    out_count = 2'd0 ;
end

always @(posedge clk_in) begin
    if (WE) begin
        RAM[in_count[1:0]] <= Din;
        if (in_count[2]&&out_count[2]) begin
            in_count <= {1'b0,in_count[1:0]}+1'b1;
            out_count <= {1'b0,out_count[1:0]} ;
        end else begin
            in_count <= in_count+1'b1 ;
        end
    end
end

always @(posedge clk_out) begin
    if (RE) begin
        Dout <= RAM[out_count[1:0]] ;
        if (in_count[2]&&out_count[2]) begin
            out_count <= {1'b0,out_count[1:0]}+1'b1;
            in_count <= {1'b0,in_count[1:0]};
        end else begin
            out_count <= out_count+1'b1 ;
        end
    end
end

assign n_full = ~(in_count==out_count+3'd3) ;
assign n_empty = ~(in_count==out_count) ;

endmodule

MAC_HW_plus/SRAM_1.v
module SRAM_1 (
    input [3:0] addr ,
    output reg [`DATA_WIDTH-1:0] Dout ,
    input EN ,
    input clk 
);
reg [`DATA_WIDTH-1:0] RAM [8:0] ;
initial begin

    RAM[0]=1;

    RAM[1]=6;

    RAM[2]=5;

    RAM[3]=0;

    // other addr
    RAM[4]=0;
    RAM[5]=0;
    RAM[6]=0;
    RAM[7]=0;
    RAM[8]=0;

end

always @(posedge clk) begin
    if (EN) begin
        Dout <= RAM[addr] ;
    end
end
    
endmodule

MAC_HW_plus/SRAM_0.v
module SRAM_0 (
    input [3:0] addr ,
    output reg [`DATA_WIDTH-1:0] Dout ,
    input EN ,
    input clk 
);
reg [`DATA_WIDTH-1:0] RAM [8:0] ;
initial begin
    RAM[0]=3;
    RAM[1]=1;
    RAM[2]=2;
    RAM[3]=6;
    RAM[4]=0;
    RAM[5]=5;
    RAM[6]=0;
    RAM[7]=0;
    RAM[8]=3;
    // other addr
end

always @(posedge clk) begin
    if (EN) begin
        Dout <= RAM[addr] ;
    end
end
    
endmodule

MAC_HW_plus/system.v
`timescale 1ns/1ns
`include "param.v"
`include "SRAM_0.v"
`include "SRAM_1.v"
`include "FIFO_64x4.v"
`include "MAC_new.v"
module system ();
initial begin
    $dumpfile("MACsystem.vcd");
    $dumpvars();
end
reg clk_slow ;
initial begin
    clk_slow = 0;
    forever begin
        #7 clk_slow = (~clk_slow);
    end
end    
reg clk_quick ;
initial begin
    clk_quick = 0;
    forever begin
        #5 clk_quick = (~clk_quick);
    end
end    
initial begin
    #5000 ;
    $finish ;
end

// controller
wire WE , RE , n_empty , n_full ;
assign WE = n_full ;
assign RE = n_empty ;

// golden test data 
reg [`DATA_WIDTH-1:0] golden_mult , golden_add ;
initial begin
    golden_add = 3+1+2+6+0+5+0+0+3;
    golden_mult = 0 ;
end
localparam RESET_mult = 2'd0 ;
localparam RESET_add = 2'd3 ;
localparam MULT = 2'd1;
localparam ADD  = 2'd2;
reg [1:0] mode ;
initial begin
    mode= 0 ;
end
wire [`DATA_WIDTH-1:0] ramout0 , ramout1 ;
reg [3:0] addr_0 , addr_1 ;
initial begin
    addr_0 = 0 ;
    addr_1 = 0 ;
end
reg [3:0] count ;
initial begin 
    count = 0 ;
end
always @(posedge clk_quick) begin
    if (mode==MULT) begin
        if (mac_out==golden_mult) begin
            addr_0 <= 0 ;
            addr_1 <= 0 ;
            mode<=RESET_add;
            $display("MULT result = %d.",mac_out);
            $display("MULT TEST PASS");
        end else if (WE) begin
            addr_0 <= (addr_0==8)?(0):(addr_0+1) ;
            addr_1 <= 0 ;
        end
    end else if (mode==ADD) begin
        if (mac_out==golden_add) begin
            addr_0 <= 0 ;
            addr_1 <= 0 ;
            mode<=MULT;
            $display("ADD result = %d.",mac_out);
            $display("ADD TEST PASS");
            $finish ;
        end else if (WE) begin
                addr_0 <= (addr_0==8)?(0):(addr_0+1) ;
                addr_1 <= 0 ;
        end
    end else if (mode==RESET_mult) begin
        if (mac_out==0) begin
            addr_0 <= 0 ;
            addr_1 <= 0 ;
            mode<=MULT;
        end else begin
            addr_0 <= 1 ; // zero
            addr_1 <= 0 ;
        end
    end else if (mode==RESET_add) begin
        if (count==4'd8) begin
            addr_0 <= 0 ;
            addr_1 <= 0 ;
            count <= 0 ;
            mode<=ADD;
        end else begin
            count <= count+1;
            addr_0 <= 7 ; // zero
            addr_1 <= 7 ;
        end
    end
end
SRAM_0 SRAM0(.addr(addr_0),   .EN(WE),  .clk(clk_quick), .Dout(ramout0));
SRAM_1 SRAM1(.addr(addr_1),   .EN(WE),  .clk(clk_quick), .Dout(ramout1));

// output n_full , input [`DATA_WIDTH-1:0] Din , output reg [`DATA_WIDTH-1:0] Dout , input clk_in , input clk_out , input WE , input RE , output n_empty
wire [`DATA_WIDTH-1:0] data_0 , data_1 ;
FIFO_64x4 FIFO0(.n_full(n_full),  .Din(ramout0), .Dout(data_0), .clk_in(clk_quick),  .clk_out(clk_slow), .WE(WE),  .RE(RE),  .n_empty(n_empty));
FIFO_64x4 FIFO1(.n_full(),  .Din(ramout1), .Dout(data_1),   .clk_in(clk_quick),  .clk_out(clk_slow), .WE(WE),  .RE(RE),  .n_empty());

wire [`DATA_WIDTH-1:0] mac_out ;
reg mulsel , addsel ;
MAC_new DUT(.clk(clk_slow), .mulsel(mulsel),  .addsel(addsel),  .data_0(data_0),  .data_1(data_1),  .mac_out(mac_out));
always @(*) begin
    case (mode)
        MULT: begin
            mulsel = 1 ;
            addsel = 0 ;
        end 
        ADD : begin
            mulsel = 0 ;
            addsel = 1 ;
        end
        default: begin
            mulsel = 0 ;
            addsel = 0 ;
        end
    endcase
end
    
endmodule

MAC_HW_plus/build/MACsystem.vcd
$date
	Tue Oct 24 14:41:42 2023
$end
$version
	Icarus Verilog
$end
$timescale
	1ns
$end
$scope module system $end
$var wire 1 ! RE $end
$var wire 1 " WE $end
$var wire 64 # ramout1 [63:0] $end
$var wire 64 $ ramout0 [63:0] $end
$var wire 1 % n_full $end
$var wire 1 & n_empty $end
$var wire 64 ' mac_out [63:0] $end
$var wire 64 ( data_1 [63:0] $end
$var wire 64 ) data_0 [63:0] $end
$var reg 4 * addr_0 [3:0] $end
$var reg 4 + addr_1 [3:0] $end
$var reg 1 , addsel $end
$var reg 1 - clk_quick $end
$var reg 1 . clk_slow $end
$var reg 4 / count [3:0] $end
$var reg 64 0 golden_add [63:0] $end
$var reg 64 1 golden_mult [63:0] $end
$var reg 2 2 mode [1:0] $end
$var reg 1 3 mulsel $end
$scope module DUT $end
$var wire 1 , addsel $end
$var wire 1 . clk $end
$var wire 1 3 mulsel $end
$var wire 64 4 data_1 [63:0] $end
$var wire 64 5 data_0 [63:0] $end
$var reg 64 6 mac_out [63:0] $end
$var reg 64 7 mult_out [63:0] $end
$upscope $end
$scope module FIFO0 $end
$var wire 1 ! RE $end
$var wire 1 " WE $end
$var wire 1 - clk_in $end
$var wire 1 . clk_out $end
$var wire 1 & n_empty $end
$var wire 1 % n_full $end
$var wire 64 8 Din [63:0] $end
$var reg 64 9 Dout [63:0] $end
$var reg 3 : in_count [2:0] $end
$var reg 3 ; out_count [2:0] $end
$upscope $end
$scope module FIFO1 $end
$var wire 1 ! RE $end
$var wire 1 " WE $end
$var wire 1 - clk_in $end
$var wire 1 . clk_out $end
$var wire 1 < n_empty $end
$var wire 1 = n_full $end
$var wire 64 > Din [63:0] $end
$var reg 64 ? Dout [63:0] $end
$var reg 3 @ in_count [2:0] $end
$var reg 3 A out_count [2:0] $end
$upscope $end
$scope module SRAM0 $end
$var wire 1 " EN $end
$var wire 4 B addr [3:0] $end
$var wire 1 - clk $end
$var reg 64 C Dout [63:0] $end
$upscope $end
$scope module SRAM1 $end
$var wire 1 " EN $end
$var wire 4 D addr [3:0] $end
$var wire 1 - clk $end
$var reg 64 E Dout [63:0] $end
$upscope $end
$upscope $end
$enddefinitions $end
#0
$dumpvars
bx E
b0 D
bx C
b0 B
b0 A
b0 @
bx ?
bx >
1=
0<
b0 ;
b0 :
bx 9
bx 8
b1 7
bx 6
bx 5
bx 4
03
b0 2
b0 1
b10100 0
b0 /
0.
0-
0,
b0 +
b0 *
bx )
bx (
bx '
0&
1%
bx $
bx #
1"
0!
$end
#5
1!
1&
1<
b11 $
b11 8
b11 C
b1 #
b1 >
b1 E
b1 :
b1 @
b1 *
b1 B
1-
#7
0!
0&
0<
b1 ;
b1 A
b1 '
b1 6
bx 7
1.
#10
0-
#14
0.
#15
1<
1!
1&
b10 @
b10 :
b1 $
b1 8
b1 C
1-
#20
0-
#21
0<
0!
0&
bx '
bx 6
b10 A
b1 (
b1 4
b1 ?
b10 ;
b11 )
b11 5
b11 9
1.
#25
1!
1&
1<
b11 :
b11 @
1-
#28
0.
#30
0-
#35
b100 @
b100 :
b11 ;
b1 )
b1 5
b1 9
b11 A
b11 7
1-
1.
#40
0-
#42
0.
#45
b101 :
b101 @
1-
#49
b11 '
b11 6
b1 7
b100 A
b100 ;
1.
#50
0-
#55
b0 A
b10 @
b0 ;
b10 :
1-
#56
0.
#60
0-
#63
b1 ;
b1 A
b1 '
b1 6
1.
#65
b11 :
b11 @
1-
#70
0-
0.
#75
0=
0"
0%
b100 @
b100 :
1-
#77
1=
1"
1%
b10 A
b10 ;
1.
#80
0-
#84
0.
#85
0"
0%
0=
b101 :
b101 @
1-
#90
0-
#91
1"
1%
1=
b11 ;
b11 A
1.
#95
0=
0"
0%
b110 @
b110 :
1-
#98
0.
#100
0-
#105
1=
1"
1%
b100 A
b100 ;
1-
1.
#110
0-
#112
0.
#115
0=
0"
0%
b0 A
b11 @
b0 ;
b11 :
1-
#119
1"
1%
1=
b1 ;
b1 A
1.
#120
0-
#125
0"
0%
0=
b100 :
b100 @
1-
#126
0.
#130
0-
#133
1=
1"
1%
b10 A
b10 ;
1.
#135
0=
0"
0%
b101 @
b101 :
1-
#140
0-
0.
#145
1-
#147
1"
1%
1=
b11 ;
b11 A
1.
#150
0-
#154
0.
#155
0=
0"
0%
b110 @
b110 :
1-
#160
0-
#161
1=
1"
1%
b100 A
b100 ;
1.
#165
0"
0%
0=
b0 ;
b11 :
b0 A
b11 @
1-
#168
0.
#170
0-
#175
1"
1%
1=
b1 ;
b1 A
1-
1.
#180
0-
#182
0.
#185
0"
0%
0=
b100 :
b100 @
1-
#189
1=
1"
1%
b10 A
b10 ;
1.
#190
0-
#195
0=
0"
0%
b101 @
b101 :
1-
#196
0.
#200
0-
#203
1"
1%
1=
b11 ;
b11 A
1.
#205
0"
0%
0=
b110 :
b110 @
1-
#210
0-
0.
#215
1-
#217
1=
1"
1%
b100 A
b100 ;
1.
#220
0-
#224
0.
#225
0"
0%
0=
b0 ;
b11 :
b0 A
b11 @
1-
#230
0-
#231
1"
1%
1=
b1 ;
b1 A
1.
#235
0=
0"
0%
b100 @
b100 :
1-
#238
0.
#240
0-
#245
1=
1"
1%
b10 A
b10 ;
1-
1.
#250
0-
#252
0.
#255
0=
0"
0%
b101 @
b101 :
1-
#259
1"
1%
1=
b11 ;
b11 A
1.
#260
0-
#265
0"
0%
0=
b110 :
b110 @
1-
#266
0.
#270
0-
#273
1=
1"
1%
b100 A
b100 ;
1.
#275
0=
0"
0%
b0 A
b11 @
b0 ;
b11 :
1-
#280
0-
0.
#285
1-
#287
1"
1%
1=
b1 ;
b1 A
1.
#290
0-
#294
0.
#295
0=
0"
0%
b100 @
b100 :
1-
#300
0-
#301
1=
1"
1%
b10 A
b10 ;
1.
#305
0"
0%
0=
b101 :
b101 @
1-
#308
0.
#310
0-
#315
1"
1%
1=
b11 ;
b11 A
1-
1.
#320
0-
#322
0.
#325
0"
0%
0=
b110 :
b110 @
1-
#329
1=
1"
1%
b100 A
b100 ;
1.
#330
0-
#335
0=
0"
0%
b0 A
b11 @
b0 ;
b11 :
1-
#336
0.
#340
0-
#343
1"
1%
1=
b1 ;
b1 A
1.
#345
0"
0%
0=
b100 :
b100 @
1-
#350
0-
0.
#355
1-
#357
1=
1"
1%
b10 A
b10 ;
1.
#360
0-
#364
0.
#365
0"
0%
0=
b101 :
b101 @
1-
#370
0-
#371
1"
1%
1=
b11 ;
b11 A
1.
#375
0=
0"
0%
b110 @
b110 :
1-
#378
0.
#380
0-
#385
1=
1"
1%
b100 A
b100 ;
1-
1.
#390
0-
#392
0.
#395
0=
0"
0%
b0 A
b11 @
b0 ;
b11 :
1-
#399
1"
1%
1=
b1 ;
b1 A
1.
#400
0-
#405
0"
0%
0=
b100 :
b100 @
1-
#406
0.
#410
0-
#413
1=
1"
1%
b10 A
b10 ;
1.
#415
0=
0"
0%
b101 @
b101 :
1-
#420
0-
0.
#425
1-
#427
1"
1%
1=
b11 ;
b11 A
1.
#430
0-
#434
0.
#435
0=
0"
0%
b110 @
b110 :
1-
#440
0-
#441
1=
1"
1%
b100 A
b100 ;
1.
#445
0"
0%
0=
b0 ;
b11 :
b0 A
b11 @
1-
#448
0.
#450
0-
#455
1"
1%
1=
b1 ;
b1 A
1-
1.
#460
0-
#462
0.
#465
0"
0%
0=
b100 :
b100 @
1-
#469
1=
1"
1%
b10 A
b10 ;
1.
#470
0-
#475
0=
0"
0%
b101 @
b101 :
1-
#476
0.
#480
0-
#483
1"
1%
1=
b11 ;
b11 A
1.
#485
0"
0%
0=
b110 :
b110 @
1-
#490
0-
0.
#495
1-
#497
1=
1"
1%
b100 A
b100 ;
1.
#500
0-
#504
0.
#505
0"
0%
0=
b0 ;
b11 :
b0 A
b11 @
1-
#510
0-
#511
1"
1%
1=
b1 ;
b1 A
1.
#515
0=
0"
0%
b100 @
b100 :
1-
#518
0.
#520
0-
#525
1=
1"
1%
b10 A
b10 ;
1-
1.
#530
0-
#532
0.
#535
0=
0"
0%
b101 @
b101 :
1-
#539
1"
1%
1=
b11 ;
b11 A
1.
#540
0-
#545
0"
0%
0=
b110 :
b110 @
1-
#546
0.
#550
0-
#553
1=
1"
1%
b100 A
b100 ;
1.
#555
0=
0"
0%
b0 A
b11 @
b0 ;
b11 :
1-
#560
0-
0.
#565
1-
#567
1"
1%
1=
b1 ;
b1 A
1.
#570
0-
#574
0.
#575
0=
0"
0%
b100 @
b100 :
1-
#580
0-
#581
1=
1"
1%
b10 A
b10 ;
1.
#585
0"
0%
0=
b101 :
b101 @
1-
#588
0.
#590
0-
#595
1"
1%
1=
b11 ;
b11 A
1-
1.
#600
0-
#602
0.
#605
0"
0%
0=
b110 :
b110 @
1-
#609
1=
1"
1%
b100 A
b100 ;
1.
#610
0-
#615
0=
0"
0%
b0 A
b11 @
b0 ;
b11 :
1-
#616
0.
#620
0-
#623
1"
1%
1=
b1 ;
b1 A
1.
#625
0"
0%
0=
b100 :
b100 @
1-
#630
0-
0.
#635
1-
#637
1=
1"
1%
b10 A
b10 ;
1.
#640
0-
#644
0.
#645
0"
0%
0=
b101 :
b101 @
1-
#650
0-
#651
1"
1%
1=
b11 ;
b11 A
1.
#655
0=
0"
0%
b110 @
b110 :
1-
#658
0.
#660
0-
#665
1=
1"
1%
b100 A
b100 ;
1-
1.
#670
0-
#672
0.
#675
0=
0"
0%
b0 A
b11 @
b0 ;
b11 :
1-
#679
1"
1%
1=
b1 ;
b1 A
1.
#680
0-
#685
0"
0%
0=
b100 :
b100 @
1-
#686
0.
#690
0-
#693
1=
1"
1%
b10 A
b10 ;
1.
#695
0=
0"
0%
b101 @
b101 :
1-
#700
0-
0.
#705
1-
#707
1"
1%
1=
b11 ;
b11 A
1.
#710
0-
#714
0.
#715
0=
0"
0%
b110 @
b110 :
1-
#720
0-
#721
1=
1"
1%
b100 A
b100 ;
1.
#725
0"
0%
0=
b0 ;
b11 :
b0 A
b11 @
1-
#728
0.
#730
0-
#735
1"
1%
1=
b1 ;
b1 A
1-
1.
#740
0-
#742
0.
#745
0"
0%
0=
b100 :
b100 @
1-
#749
1=
1"
1%
b10 A
b10 ;
1.
#750
0-
#755
0=
0"
0%
b101 @
b101 :
1-
#756
0.
#760
0-
#763
1"
1%
1=
b11 ;
b11 A
1.
#765
0"
0%
0=
b110 :
b110 @
1-
#770
0-
0.
#775
1-
#777
1=
1"
1%
b100 A
b100 ;
1.
#780
0-
#784
0.
#785
0"
0%
0=
b0 ;
b11 :
b0 A
b11 @
1-
#790
0-
#791
1"
1%
1=
b1 ;
b1 A
1.
#795
0=
0"
0%
b100 @
b100 :
1-
#798
0.
#800
0-
#805
1=
1"
1%
b10 A
b10 ;
1-
1.
#810
0-
#812
0.
#815
0=
0"
0%
b101 @
b101 :
1-
#819
1"
1%
1=
b11 ;
b11 A
1.
#820
0-
#825
0"
0%
0=
b110 :
b110 @
1-
#826
0.
#830
0-
#833
1=
1"
1%
b100 A
b100 ;
1.
#835
0=
0"
0%
b0 A
b11 @
b0 ;
b11 :
1-
#840
0-
0.
#845
1-
#847
1"
1%
1=
b1 ;
b1 A
1.
#850
0-
#854
0.
#855
0=
0"
0%
b100 @
b100 :
1-
#860
0-
#861
1=
1"
1%
b10 A
b10 ;
1.
#865
0"
0%
0=
b101 :
b101 @
1-
#868
0.
#870
0-
#875
1"
1%
1=
b11 ;
b11 A
1-
1.
#880
0-
#882
0.
#885
0"
0%
0=
b110 :
b110 @
1-
#889
1=
1"
1%
b100 A
b100 ;
1.
#890
0-
#895
0=
0"
0%
b0 A
b11 @
b0 ;
b11 :
1-
#896
0.
#900
0-
#903
1"
1%
1=
b1 ;
b1 A
1.
#905
0"
0%
0=
b100 :
b100 @
1-
#910
0-
0.
#915
1-
#917
1=
1"
1%
b10 A
b10 ;
1.
#920
0-
#924
0.
#925
0"
0%
0=
b101 :
b101 @
1-
#930
0-
#931
1"
1%
1=
b11 ;
b11 A
1.
#935
0=
0"
0%
b110 @
b110 :
1-
#938
0.
#940
0-
#945
1=
1"
1%
b100 A
b100 ;
1-
1.
#950
0-
#952
0.
#955
0=
0"
0%
b0 A
b11 @
b0 ;
b11 :
1-
#959
1"
1%
1=
b1 ;
b1 A
1.
#960
0-
#965
0"
0%
0=
b100 :
b100 @
1-
#966
0.
#970
0-
#973
1=
1"
1%
b10 A
b10 ;
1.
#975
0=
0"
0%
b101 @
b101 :
1-
#980
0-
0.
#985
1-
#987
1"
1%
1=
b11 ;
b11 A
1.
#990
0-
#994
0.
#995
0=
0"
0%
b110 @
b110 :
1-
#1000
0-
#1001
1=
1"
1%
b100 A
b100 ;
1.
#1005
0"
0%
0=
b0 ;
b11 :
b0 A
b11 @
1-
#1008
0.
#1010
0-
#1015
1"
1%
1=
b1 ;
b1 A
1-
1.
#1020
0-
#1022
0.
#1025
0"
0%
0=
b100 :
b100 @
1-
#1029
1=
1"
1%
b10 A
b10 ;
1.
#1030
0-
#1035
0=
0"
0%
b101 @
b101 :
1-
#1036
0.
#1040
0-
#1043
1"
1%
1=
b11 ;
b11 A
1.
#1045
0"
0%
0=
b110 :
b110 @
1-
#1050
0-
0.
#1055
1-
#1057
1=
1"
1%
b100 A
b100 ;
1.
#1060
0-
#1064
0.
#1065
0"
0%
0=
b0 ;
b11 :
b0 A
b11 @
1-
#1070
0-
#1071
1"
1%
1=
b1 ;
b1 A
1.
#1075
0=
0"
0%
b100 @
b100 :
1-
#1078
0.
#1080
0-
#1085
1=
1"
1%
b10 A
b10 ;
1-
1.
#1090
0-
#1092
0.
#1095
0=
0"
0%
b101 @
b101 :
1-
#1099
1"
1%
1=
b11 ;
b11 A
1.
#1100
0-
#1105
0"
0%
0=
b110 :
b110 @
1-
#1106
0.
#1110
0-
#1113
1=
1"
1%
b100 A
b100 ;
1.
#1115
0=
0"
0%
b0 A
b11 @
b0 ;
b11 :
1-
#1120
0-
0.
#1125
1-
#1127
1"
1%
1=
b1 ;
b1 A
1.
#1130
0-
#1134
0.
#1135
0=
0"
0%
b100 @
b100 :
1-
#1140
0-
#1141
1=
1"
1%
b10 A
b10 ;
1.
#1145
0"
0%
0=
b101 :
b101 @
1-
#1148
0.
#1150
0-
#1155
1"
1%
1=
b11 ;
b11 A
1-
1.
#1160
0-
#1162
0.
#1165
0"
0%
0=
b110 :
b110 @
1-
#1169
1=
1"
1%
b100 A
b100 ;
1.
#1170
0-
#1175
0=
0"
0%
b0 A
b11 @
b0 ;
b11 :
1-
#1176
0.
#1180
0-
#1183
1"
1%
1=
b1 ;
b1 A
1.
#1185
0"
0%
0=
b100 :
b100 @
1-
#1190
0-
0.
#1195
1-
#1197
1=
1"
1%
b10 A
b10 ;
1.
#1200
0-
#1204
0.
#1205
0"
0%
0=
b101 :
b101 @
1-
#1210
0-
#1211
1"
1%
1=
b11 ;
b11 A
1.
#1215
0=
0"
0%
b110 @
b110 :
1-
#1218
0.
#1220
0-
#1225
1=
1"
1%
b100 A
b100 ;
1-
1.
#1230
0-
#1232
0.
#1235
0=
0"
0%
b0 A
b11 @
b0 ;
b11 :
1-
#1239
1"
1%
1=
b1 ;
b1 A
1.
#1240
0-
#1245
0"
0%
0=
b100 :
b100 @
1-
#1246
0.
#1250
0-
#1253
1=
1"
1%
b10 A
b10 ;
1.
#1255
0=
0"
0%
b101 @
b101 :
1-
#1260
0-
0.
#1265
1-
#1267
1"
1%
1=
b11 ;
b11 A
1.
#1270
0-
#1274
0.
#1275
0=
0"
0%
b110 @
b110 :
1-
#1280
0-
#1281
1=
1"
1%
b100 A
b100 ;
1.
#1285
0"
0%
0=
b0 ;
b11 :
b0 A
b11 @
1-
#1288
0.
#1290
0-
#1295
1"
1%
1=
b1 ;
b1 A
1-
1.
#1300
0-
#1302
0.
#1305
0"
0%
0=
b100 :
b100 @
1-
#1309
1=
1"
1%
b10 A
b10 ;
1.
#1310
0-
#1315
0=
0"
0%
b101 @
b101 :
1-
#1316
0.
#1320
0-
#1323
1"
1%
1=
b11 ;
b11 A
1.
#1325
0"
0%
0=
b110 :
b110 @
1-
#1330
0-
0.
#1335
1-
#1337
1=
1"
1%
b100 A
b100 ;
1.
#1340
0-
#1344
0.
#1345
0"
0%
0=
b0 ;
b11 :
b0 A
b11 @
1-
#1350
0-
#1351
1"
1%
1=
b1 ;
b1 A
1.
#1355
0=
0"
0%
b100 @
b100 :
1-
#1358
0.
#1360
0-
#1365
1=
1"
1%
b10 A
b10 ;
1-
1.
#1370
0-
#1372
0.
#1375
0=
0"
0%
b101 @
b101 :
1-
#1379
1"
1%
1=
b11 ;
b11 A
1.
#1380
0-
#1385
0"
0%
0=
b110 :
b110 @
1-
#1386
0.
#1390
0-
#1393
1=
1"
1%
b100 A
b100 ;
1.
#1395
0=
0"
0%
b0 A
b11 @
b0 ;
b11 :
1-
#1400
0-
0.
#1405
1-
#1407
1"
1%
1=
b1 ;
b1 A
1.
#1410
0-
#1414
0.
#1415
0=
0"
0%
b100 @
b100 :
1-
#1420
0-
#1421
1=
1"
1%
b10 A
b10 ;
1.
#1425
0"
0%
0=
b101 :
b101 @
1-
#1428
0.
#1430
0-
#1435
1"
1%
1=
b11 ;
b11 A
1-
1.
#1440
0-
#1442
0.
#1445
0"
0%
0=
b110 :
b110 @
1-
#1449
1=
1"
1%
b100 A
b100 ;
1.
#1450
0-
#1455
0=
0"
0%
b0 A
b11 @
b0 ;
b11 :
1-
#1456
0.
#1460
0-
#1463
1"
1%
1=
b1 ;
b1 A
1.
#1465
0"
0%
0=
b100 :
b100 @
1-
#1470
0-
0.
#1475
1-
#1477
1=
1"
1%
b10 A
b10 ;
1.
#1480
0-
#1484
0.
#1485
0"
0%
0=
b101 :
b101 @
1-
#1490
0-
#1491
1"
1%
1=
b11 ;
b11 A
1.
#1495
0=
0"
0%
b110 @
b110 :
1-
#1498
0.
#1500
0-
#1505
1=
1"
1%
b100 A
b100 ;
1-
1.
#1510
0-
#1512
0.
#1515
0=
0"
0%
b0 A
b11 @
b0 ;
b11 :
1-
#1519
1"
1%
1=
b1 ;
b1 A
1.
#1520
0-
#1525
0"
0%
0=
b100 :
b100 @
1-
#1526
0.
#1530
0-
#1533
1=
1"
1%
b10 A
b10 ;
1.
#1535
0=
0"
0%
b101 @
b101 :
1-
#1540
0-
0.
#1545
1-
#1547
1"
1%
1=
b11 ;
b11 A
1.
#1550
0-
#1554
0.
#1555
0=
0"
0%
b110 @
b110 :
1-
#1560
0-
#1561
1=
1"
1%
b100 A
b100 ;
1.
#1565
0"
0%
0=
b0 ;
b11 :
b0 A
b11 @
1-
#1568
0.
#1570
0-
#1575
1"
1%
1=
b1 ;
b1 A
1-
1.
#1580
0-
#1582
0.
#1585
0"
0%
0=
b100 :
b100 @
1-
#1589
1=
1"
1%
b10 A
b10 ;
1.
#1590
0-
#1595
0=
0"
0%
b101 @
b101 :
1-
#1596
0.
#1600
0-
#1603
1"
1%
1=
b11 ;
b11 A
1.
#1605
0"
0%
0=
b110 :
b110 @
1-
#1610
0-
0.
#1615
1-
#1617
1=
1"
1%
b100 A
b100 ;
1.
#1620
0-
#1624
0.
#1625
0"
0%
0=
b0 ;
b11 :
b0 A
b11 @
1-
#1630
0-
#1631
1"
1%
1=
b1 ;
b1 A
1.
#1635
0=
0"
0%
b100 @
b100 :
1-
#1638
0.
#1640
0-
#1645
1=
1"
1%
b10 A
b10 ;
1-
1.
#1650
0-
#1652
0.
#1655
0=
0"
0%
b101 @
b101 :
1-
#1659
1"
1%
1=
b11 ;
b11 A
1.
#1660
0-
#1665
0"
0%
0=
b110 :
b110 @
1-
#1666
0.
#1670
0-
#1673
1=
1"
1%
b100 A
b100 ;
1.
#1675
0=
0"
0%
b0 A
b11 @
b0 ;
b11 :
1-
#1680
0-
0.
#1685
1-
#1687
1"
1%
1=
b1 ;
b1 A
1.
#1690
0-
#1694
0.
#1695
0=
0"
0%
b100 @
b100 :
1-
#1700
0-
#1701
1=
1"
1%
b10 A
b10 ;
1.
#1705
0"
0%
0=
b101 :
b101 @
1-
#1708
0.
#1710
0-
#1715
1"
1%
1=
b11 ;
b11 A
1-
1.
#1720
0-
#1722
0.
#1725
0"
0%
0=
b110 :
b110 @
1-
#1729
1=
1"
1%
b100 A
b100 ;
1.
#1730
0-
#1735
0=
0"
0%
b0 A
b11 @
b0 ;
b11 :
1-
#1736
0.
#1740
0-
#1743
1"
1%
1=
b1 ;
b1 A
1.
#1745
0"
0%
0=
b100 :
b100 @
1-
#1750
0-
0.
#1755
1-
#1757
1=
1"
1%
b10 A
b10 ;
1.
#1760
0-
#1764
0.
#1765
0"
0%
0=
b101 :
b101 @
1-
#1770
0-
#1771
1"
1%
1=
b11 ;
b11 A
1.
#1775
0=
0"
0%
b110 @
b110 :
1-
#1778
0.
#1780
0-
#1785
1=
1"
1%
b100 A
b100 ;
1-
1.
#1790
0-
#1792
0.
#1795
0=
0"
0%
b0 A
b11 @
b0 ;
b11 :
1-
#1799
1"
1%
1=
b1 ;
b1 A
1.
#1800
0-
#1805
0"
0%
0=
b100 :
b100 @
1-
#1806
0.
#1810
0-
#1813
1=
1"
1%
b10 A
b10 ;
1.
#1815
0=
0"
0%
b101 @
b101 :
1-
#1820
0-
0.
#1825
1-
#1827
1"
1%
1=
b11 ;
b11 A
1.
#1830
0-
#1834
0.
#1835
0=
0"
0%
b110 @
b110 :
1-
#1840
0-
#1841
1=
1"
1%
b100 A
b100 ;
1.
#1845
0"
0%
0=
b0 ;
b11 :
b0 A
b11 @
1-
#1848
0.
#1850
0-
#1855
1"
1%
1=
b1 ;
b1 A
1-
1.
#1860
0-
#1862
0.
#1865
0"
0%
0=
b100 :
b100 @
1-
#1869
1=
1"
1%
b10 A
b10 ;
1.
#1870
0-
#1875
0=
0"
0%
b101 @
b101 :
1-
#1876
0.
#1880
0-
#1883
1"
1%
1=
b11 ;
b11 A
1.
#1885
0"
0%
0=
b110 :
b110 @
1-
#1890
0-
0.
#1895
1-
#1897
1=
1"
1%
b100 A
b100 ;
1.
#1900
0-
#1904
0.
#1905
0"
0%
0=
b0 ;
b11 :
b0 A
b11 @
1-
#1910
0-
#1911
1"
1%
1=
b1 ;
b1 A
1.
#1915
0=
0"
0%
b100 @
b100 :
1-
#1918
0.
#1920
0-
#1925
1=
1"
1%
b10 A
b10 ;
1-
1.
#1930
0-
#1932
0.
#1935
0=
0"
0%
b101 @
b101 :
1-
#1939
1"
1%
1=
b11 ;
b11 A
1.
#1940
0-
#1945
0"
0%
0=
b110 :
b110 @
1-
#1946
0.
#1950
0-
#1953
1=
1"
1%
b100 A
b100 ;
1.
#1955
0=
0"
0%
b0 A
b11 @
b0 ;
b11 :
1-
#1960
0-
0.
#1965
1-
#1967
1"
1%
1=
b1 ;
b1 A
1.
#1970
0-
#1974
0.
#1975
0=
0"
0%
b100 @
b100 :
1-
#1980
0-
#1981
1=
1"
1%
b10 A
b10 ;
1.
#1985
0"
0%
0=
b101 :
b101 @
1-
#1988
0.
#1990
0-
#1995
1"
1%
1=
b11 ;
b11 A
1-
1.
#2000
0-
#2002
0.
#2005
0"
0%
0=
b110 :
b110 @
1-
#2009
1=
1"
1%
b100 A
b100 ;
1.
#2010
0-
#2015
0=
0"
0%
b0 A
b11 @
b0 ;
b11 :
1-
#2016
0.
#2020
0-
