MAC_HW_plus/param.v
`define DATA_WIDTH 64

MAC_HW_plus/FIFO_64x4.v
`include "param.v"

module FIFO_64x4
// #(parameter DATA_WIDTH = `DATA_WIDTH)
(output n_full , input [`DATA_WIDTH-1:0] Din , output reg [`DATA_WIDTH-1:0] Dout , input clk_in , input clk_out , input WE , input RE , output n_empty);
reg [`DATA_WIDTH-1:0] RAM [0:3] ; 
reg [2:0] in_count , out_count ;
initial begin
    in_count = 2'd0 ;
    out_count = 2'd0 ;
end

always @(posedge clk_in) begin
    if (WE) begin
        RAM[in_count[1:0]] <= Din;
        if (in_count[2]&&out_count[2]) begin
            in_count <= {1'b0,in_count[1:0]}+1'b1;
            out_count <= {1'b0,out_count[1:0]} ;
        end else begin
            in_count <= in_count+1'b1 ;
        end
    end
end

always @(posedge clk_out) begin
    if (RE) begin
        Dout <= RAM[out_count[1:0]] ;
        if (in_count[2]&&out_count[2]) begin
            out_count <= {1'b0,out_count[1:0]}+1'b1;
            in_count <= {1'b0,in_count[1:0]};
        end else begin
            out_count <= out_count+1'b1 ;
        end
    end
end

assign n_full = ~(in_count==out_count+3'd3) ;
assign n_empty = ~(in_count==out_count) ;

endmodule

MAC_HW_plus/test_FIFO.v
`include "FIFO_64x4.v"

module test_FIFO ();
wire n_full ,n_empty;
reg WE , RE ;
reg clk_in , clk_out ;
reg [63:0] Din ;
initial begin
    Din = 64'd1;
end
wire [63:0] Dout ;

initial begin
    $dumpfile("test_FIFO.vcd");
    $dumpvars();
end

initial begin
    clk_in = 0;
    forever begin
        #5 clk_in = (~clk_in);
    end
end


initial begin
    clk_out = 0;
    forever begin
        #7 clk_out = (~clk_out);
    end
end    

always @(posedge clk_in) begin
    if (WE) begin
        Din <= Din + 1'b1 ;
    end 
end
always @(*) begin
    WE = n_full ;
end
always @(*) begin
    RE = n_empty;
end


initial begin
    #500 ;
    $finish ;
end

FIFO_64x4 DUT1(.n_full(n_full),.Din(Din) ,.Dout(Dout) ,.clk_in(clk_in) ,.clk_out(clk_out) ,.WE(WE) ,.RE(RE),.n_empty(n_empty));
endmodule

MAC_HW_plus/test_FIFO.vcd
$date
	Tue Oct 24 11:19:48 2023
$end
$version
	Icarus Verilog
$end
$timescale
	1s
$end
$scope module test_FIFO $end
$var wire 1 ! n_full $end
$var wire 1 " n_empty $end
$var wire 64 # Dout [63:0] $end
$var reg 64 $ Din [63:0] $end
$var reg 1 % RE $end
$var reg 1 & WE $end
$var reg 1 ' clk_in $end
$var reg 1 ( clk_out $end
$scope module DUT1 $end
$var wire 64 ) Din [63:0] $end
$var wire 1 % RE $end
$var wire 1 & WE $end
$var wire 1 ' clk_in $end
$var wire 1 ( clk_out $end
$var wire 1 " n_empty $end
$var wire 1 ! n_full $end
$var reg 64 * Dout [63:0] $end
$var reg 3 + in_count [2:0] $end
$var reg 3 , out_count [2:0] $end
$upscope $end
$upscope $end
$enddefinitions $end
#0
$dumpvars
b0 ,
b0 +
bx *
b1 )
0(
0'
1&
0%
b1 $
bx #
0"
1!
$end
#5
1%
1"
b1 +
b10 $
b10 )
1'
#7
0%
0"
b1 ,
b1 #
b1 *
1(
#10
0'
#14
0(
#15
1%
1"
b11 $
b11 )
b10 +
1'
#20
0'
#21
0%
0"
b10 ,
b10 #
b10 *
1(
#25
1%
1"
b11 +
b100 $
b100 )
1'
#28
0(
#30
0'
#35
b101 $
b101 )
b100 +
b11 ,
b11 #
b11 *
1'
1(
#40
0'
#42
0(
#45
b101 +
b110 $
b110 )
1'
#49
b100 ,
b100 #
b100 *
1(
#50
0'
#55
b111 $
b111 )
b0 ,
b10 +
1'
#56
0(
#60
0'
#63
b1 ,
b101 #
b101 *
1(
#65
b11 +
b1000 $
b1000 )
1'
#70
0'
0(
#75
0&
0!
b1001 $
b1001 )
b100 +
1'
#77
1&
1!
b10 ,
b110 #
b110 *
1(
#80
0'
#84
0(
#85
0&
0!
b101 +
b1010 $
b1010 )
1'
#90
0'
#91
1&
1!
b11 ,
b111 #
b111 *
1(
#95
0&
0!
b1011 $
b1011 )
b110 +
1'
#98
0(
#100
0'
#105
1&
1!
b100 ,
b1000 #
b1000 *
1'
1(
#110
0'
#112
0(
#115
0&
0!
b1100 $
b1100 )
b0 ,
b11 +
1'
#119
1&
1!
b1 ,
b1001 #
b1001 *
1(
#120
0'
#125
0&
0!
b100 +
b1101 $
b1101 )
1'
#126
0(
#130
0'
#133
1&
1!
b10 ,
b1010 #
b1010 *
1(
#135
0&
0!
b1110 $
b1110 )
b101 +
1'
#140
0'
0(
#145
1'
#147
1&
1!
b11 ,
b1011 #
b1011 *
1(
#150
0'
#154
0(
#155
0&
0!
b1111 $
b1111 )
b110 +
1'
#160
0'
#161
1&
1!
b100 ,
b1100 #
b1100 *
1(
#165
0&
0!
b0 ,
b11 +
b10000 $
b10000 )
1'
#168
0(
#170
0'
#175
1&
1!
b1 ,
b1101 #
b1101 *
1'
1(
#180
0'
#182
0(
#185
0&
0!
b100 +
b10001 $
b10001 )
1'
#189
1&
1!
b10 ,
b1110 #
b1110 *
1(
#190
0'
#195
0&
0!
b10010 $
b10010 )
b101 +
1'
#196
0(
#200
0'
#203
1&
1!
b11 ,
b1111 #
b1111 *
1(
#205
0&
0!
b110 +
b10011 $
b10011 )
1'
#210
0'
0(
#215
1'
#217
1&
1!
b100 ,
b10000 #
b10000 *
1(
#220
0'
#224
0(
#225
0&
0!
b0 ,
b11 +
b10100 $
b10100 )
1'
#230
0'
#231
1&
1!
b1 ,
b10001 #
b10001 *
1(
#235
0&
0!
b10101 $
b10101 )
b100 +
1'
#238
0(
#240
0'
#245
1&
1!
b10 ,
b10010 #
b10010 *
1'
1(
#250
0'
#252
0(
#255
0&
0!
b10110 $
b10110 )
b101 +
1'
#259
1&
1!
b11 ,
b10011 #
b10011 *
1(
#260
0'
#265
0&
0!
b110 +
b10111 $
b10111 )
1'
#266
0(
#270
0'
#273
1&
1!
b100 ,
b10100 #
b10100 *
1(
#275
0&
0!
b11000 $
b11000 )
b0 ,
b11 +
1'
#280
0'
0(
#285
1'
#287
1&
1!
b1 ,
b10101 #
b10101 *
1(
#290
0'
#294
0(
#295
0&
0!
b11001 $
b11001 )
b100 +
1'
#300
0'
#301
1&
1!
b10 ,
b10110 #
b10110 *
1(
#305
0&
0!
b101 +
b11010 $
b11010 )
1'
#308
0(
#310
0'
#315
1&
1!
b11 ,
b10111 #
b10111 *
1'
1(
#320
0'
#322
0(
#325
0&
0!
b110 +
b11011 $
b11011 )
1'
#329
1&
1!
b100 ,
b11000 #
b11000 *
1(
#330
0'
#335
0&
0!
b11100 $
b11100 )
b0 ,
b11 +
1'
#336
0(
#340
0'
#343
1&
1!
b1 ,
b11001 #
b11001 *
1(
#345
0&
0!
b100 +
b11101 $
b11101 )
1'
#350
0'
0(
#355
1'
#357
1&
1!
b10 ,
b11010 #
b11010 *
1(
#360
0'
#364
0(
#365
0&
0!
b101 +
b11110 $
b11110 )
1'
#370
0'
#371
1&
1!
b11 ,
b11011 #
b11011 *
1(
#375
0&
0!
b11111 $
b11111 )
b110 +
1'
#378
0(
#380
0'
#385
1&
1!
b100 ,
b11100 #
b11100 *
1'
1(
#390
0'
#392
0(
#395
0&
0!
b100000 $
b100000 )
b0 ,
b11 +
1'
#399
1&
1!
b1 ,
b11101 #
b11101 *
1(
#400
0'
#405
0&
0!
b100 +
b100001 $
b100001 )
1'
#406
0(
#410
0'
#413
1&
1!
b10 ,
b11110 #
b11110 *
1(
#415
0&
0!
b100010 $
b100010 )
b101 +
1'
#420
0'
0(
#425
1'
#427
1&
1!
b11 ,
b11111 #
b11111 *
1(
#430
0'
#434
0(
#435
0&
0!
b100011 $
b100011 )
b110 +
1'
#440
0'
#441
1&
1!
b100 ,
b100000 #
b100000 *
1(
#445
0&
0!
b0 ,
b11 +
b100100 $
b100100 )
1'
#448
0(
#450
0'
#455
1&
1!
b1 ,
b100001 #
b100001 *
1'
1(
#460
0'
#462
0(
#465
0&
0!
b100 +
b100101 $
b100101 )
1'
#469
1&
1!
b10 ,
b100010 #
b100010 *
1(
#470
0'
#475
0&
0!
b100110 $
b100110 )
b101 +
1'
#476
0(
#480
0'
#483
1&
1!
b11 ,
b100011 #
b100011 *
1(
#485
0&
0!
b110 +
b100111 $
b100111 )
1'
#490
0'
0(
#495
1'
#497
1&
1!
b100 ,
b100100 #
b100100 *
1(
